sigmaker-1.6.0.dist-info/RECORD
sigmaker-1.6.0.dist-info/WHEEL
sigmaker-1.6.0.dist-info/top_level.txt
sigmaker-1.6.0.dist-info/METADATA
sigmaker-1.6.0.dist-info/licenses/LICENSE
include/simd_support.hpp
sigmaker/__init__.py
sigmaker/_speedups/simd_scan.cpp
sigmaker/_speedups/simd_scan.pxd
sigmaker/_speedups/__init__.py
sigmaker/_speedups/simd_scan.cpython-311-darwin.so
sigmaker/_speedups/simd_scan.pyx
