Metadata-Version: 2.4
Name: sigmaker
Version: 1.6.0
Summary: Sigmaker is an IDA Pro 9.0+ cross-platform signature maker plugin that works on MacOS/Linux/Windows. It creates unique binary pattern signatures to identify specific functions or addresses within binaries, even after updates. It helps reverse engineers preserve their analysis work by generating resilient signatures that can quickly relocate important code locations in new binary versions.
Author-email: Mahmoud Abdelkader <m{_no-spam_}@mahmoudimus.com>
License-Expression: MIT
Project-URL: Homepage, https://mahmoudimus.com
Project-URL: Documentation, https://github.com/mahmoudimus/ida-sigmaker/blob/main/README.md
Project-URL: Source, https://github.com/mahmoudimus/ida-sigmaker
Project-URL: Issues, https://github.com/mahmoudimus/ida-sigmaker/issues
Keywords: ida pro,signature,sigmaker,reverse engineering,binary analysis,pattern matching,disassembler,malware analysis,function identification
Classifier: Development Status :: 4 - Beta
Classifier: Environment :: Plugins
Classifier: Intended Audience :: Developers
Classifier: Operating System :: OS Independent
Classifier: Programming Language :: Python :: 3.10
Classifier: Topic :: Software Development :: Debuggers
Classifier: Topic :: Software Development :: Disassemblers
Classifier: Topic :: Software Development :: Libraries :: Python Modules
Classifier: Topic :: Software Development
Requires-Python: >=3.10
License-File: LICENSE
Provides-Extra: ci
Requires-Dist: coverage; extra == "ci"
Requires-Dist: cython>=3.1.3; extra == "ci"
Provides-Extra: speedups
Requires-Dist: cython>=3.1.3; extra == "speedups"
Dynamic: license-file
